MANIFEST.in
setup.py
strprint/__init__.py
strprint/aaa.py
strprint/libstr_print.so
strprint_test.egg-info/PKG-INFO
strprint_test.egg-info/SOURCES.txt
strprint_test.egg-info/dependency_links.txt
strprint_test.egg-info/top_level.txt