Metadata-Version: 2.1
Name: strprint_test
Version: 1.0.0
Summary: str print
Author: xxx
